git_snap-1.1.0.dist-info/licenses/LICENSE
gitsnap/__init__.py
gitsnap/cli/cli.py
gitsnap/core/__init__.py
gitsnap/core/config.py
gitsnap/core/errors.py
gitsnap/core/git_push.py
gitsnap/core/git_repo.py
gitsnap/core/snapshots.py
gitsnap/core/types.py
gitsnap/ui_gui/app.py
gitsnap/ui_gui/assets/help.md
gitsnap/ui_gui/assets/style.qss
gitsnap/ui_gui/components/__init__.py
tests/test_git_push.py
tests/test_gitrepo.py
tests/test_snapshots.py
git_snap-1.1.0.dist-info/METADATA
git_snap-1.1.0.dist-info/WHEEL
git_snap-1.1.0.dist-info/entry_points.txt
git_snap-1.1.0.dist-info/top_level.txt
git_snap-1.1.0.dist-info/RECORD
