Metadata-Version: 2.4
Name: git-snap
Version: 1.1.0
Summary: Uma ferramenta TUI Local-First que transforma o git numa máquina de 'snapshots' simples e segura.
Author-email: mefrraz <mefrraz@users.noreply.github.com>
License: MIT License
Project-URL: Homepage, https://github.com/mefrraz/git-snap
Project-URL: Bug Tracker, https://github.com/mefrraz/git-snap/issues
Keywords: git,tui,snapshot,backup,versioning
Classifier: Development Status :: 4 - Beta
Classifier: Intended Audience :: Developers
Classifier: Topic :: Software Development :: Version Control
Classifier: Topic :: System :: Archiving :: Backup
Classifier: License :: OSI Approved :: MIT License
Classifier: Programming Language :: Python :: 3
Classifier: Programming Language :: Python :: 3.8
Classifier: Programming Language :: Python :: 3.9
Classifier: Programming Language :: Python :: 3.10
Classifier: Programming Language :: Python :: 3.11
Classifier: Environment :: Console
Classifier: Topic :: Utilities
Requires-Python: >=3.8
License-File: LICENSE
Requires-Dist: PySide6>=6.6.0
Requires-Dist: markdown2>=2.4.0
Provides-Extra: test
Requires-Dist: pytest; extra == "test"
Requires-Dist: pytest-mock; extra == "test"
Dynamic: license-file
